{"list":[{"date":"2018-05","arr":{"text":["毕业酒会，老班","晚上看还挺有感觉的","温州大学校训","今天天气真好","温州大学公交车站","田子坊","田子坊夜景","上海和平饭店","再看，就把你吃掉","好多蝴蝶","怎么有点眼熟","流光溢彩的蝴蝶","猛犸象","眼镜王蛇|这是假的","紫灰蝶属","美美哒","羚羊牦牛","蓝色蝴蝶","赫脱珠凤蝶","上海世博博物馆","上海世博博物馆门口","上海泰晤士小镇钟书阁","好看的竹编","第一届英国世博会","贝尔发明的电话","金鱼灯展"],"type":["image","image","image","image","image","image","image","image","image","image","image","image","image","image","image","image","image","image","image","image","image","image","image","image","image","image"],"month":5,"link":["2018-05-05_毕业酒会，老班.jpg","2018-05-09_晚上看还挺有感觉的.jpg","2018-05-09_温州大学校训.jpg","2018-05-11_今天天气真好.jpg","2018-05-11_温州大学公交车站.jpg","2018-05-12_田子坊.jpg","2018-05-12_田子坊夜景.jpg","2018-05-13_上海和平饭店.jpg","2018-05-13_再看，就把你吃掉.jpg","2018-05-13_好多蝴蝶.jpg","2018-05-13_怎么有点眼熟.jpg","2018-05-13_流光溢彩的蝴蝶.jpg","2018-05-13_猛犸象.jpg","2018-05-13_眼镜王蛇|这是假的.jpg","2018-05-13_紫灰蝶属.jpg","2018-05-13_美美哒.jpg","2018-05-13_羚羊牦牛.jpg","2018-05-13_蓝色蝴蝶.jpg","2018-05-13_赫脱珠凤蝶.jpg","2018-05-20_上海世博博物馆.jpg","2018-05-20_上海世博博物馆门口.jpg","2018-05-20_上海泰晤士小镇钟书阁.jpg","2018-05-20_好看的竹编.jpg","2018-05-20_第一届英国世博会.jpg","2018-05-20_贝尔发明的电话.jpg","2018-05-20_金鱼灯展.jpg"],"year":2018}},{"date":"2018-04","arr":{"text":["三一八烈士墓","圆明园花1","圆明园花2","圆明园花3","圆明园花4","圆明园花5","团结湖的春天","李莉姐的花","有感觉","准备回学校","华表","教工食堂门口","校园小道","大学河畔"],"type":["image","image","image","image","image","image","image","image","image","image","image","image","image","image"],"month":4,"link":["2018-04-07_三一八烈士墓.jpg","2018-04-07_圆明园花1.jpg","2018-04-07_圆明园花2.jpg","2018-04-07_圆明园花3.jpg","2018-04-07_圆明园花4.jpg","2018-04-07_圆明园花5.jpg","2018-04-12_团结湖的春天.jpg","2018-04-16_李莉姐的花.jpg","2018-04-20_有感觉.jpg","2018-04-24_准备回学校.jpg","2018-04-26_华表.jpg","2018-04-26_教工食堂门口.jpg","2018-04-26_校园小道.jpg","2018-04-30_大学河畔.jpg"],"year":2018}}]}